simpleplayer/__init__.py
simpleplayer/longplayer.py
simpleplayer/playsong.py
simpleplayer/simpleplayer.py
simpleplayer/voicegen.py
simpleplayer-0.0.2.dist-info/LICENSE
simpleplayer-0.0.2.dist-info/METADATA
simpleplayer-0.0.2.dist-info/WHEEL
simpleplayer-0.0.2.dist-info/entry_points.txt
simpleplayer-0.0.2.dist-info/top_level.txt
simpleplayer-0.0.2.dist-info/RECORD
