Metadata-Version: 2.1
Name: simpleplayer
Version: 0.0.2
Summary: Discover the pinnacle of audio elegance with this simple-player module, boasting a sophisticated blend of advanced features and seamless compatibility across multiple platforms.
Author: Thowie Studio
Author-email: thowiestudio@gmail.com
License: MIT
License-File: LICENSE
Requires-Dist: soundfile
Requires-Dist: sounddevice
Requires-Dist: numpy
Requires-Dist: gtts
